{"trading": {"trade": 3, "market": 3, "forex": 3, "stock": 2, "price": 2, "buy": 2, "sell": 2, "currency": 2, "eurusd": 3.3, "portfolio": 2, "position": 2, "risk": 1.5, "profit": 1.5, "chart": 1.5, "signal": 2, "investigate": 0.3, "strategies": 0.3, "for": 0.3}, "news": {"news": 3, "headline": 3, "article": 2, "press": 2, "media": 2, "report": 1.5, "breaking": 2, "story": 1.5, "journalist": 2, "coverage": 1.5}, "social": {"social": 3, "twitter": 3, "reddit": 3, "sentiment": 3, "trending": 2, "viral": 2, "post": 1.5, "community": 2, "hype": 2, "crowd": 2}, "research": {"research": 3, "paper": 3, "study": 2, "hypothesis": 3, "evidence": 3, "investigate": 2.3, "experiment": 2, "cite": 2, "scientific": 2, "explain": 1.5, "are": 0.3, "poor": 0.3, "why": 0.3, "nigerians": 0.3, "most": 0.3}, "training": {"train": 3.3, "model": 3, "benchmark": 2, "optimize": 2, "hyperparameter": 3, "dataset": 2, "epoch": 2, "accuracy": 1.5, "loss": 1.5, "neural": 2, "oracle": 0.3}, "memory": {"remember": 3, "recall": 3, "history": 2, "knowledge": 2, "previous": 2, "stored": 2, "past": 1.5, "memory": 3, "retrieve": 2}, "governance": {"audit": 3, "security": 3, "compliance": 3, "violation": 2, "policy": 2, "govern": 2, "constitution": 2, "permission": 2, "threat": 2}, "creation": {"create": 2, "spawn": 3, "agent": 2, "build": 1.5, "generate": 2, "factory": 2, "capability": 2, "design": 1.5}, "coordination": {"coordinate": 3, "route": 2, "orchestrate": 3, "workflow": 2, "collaborate": 2, "delegate": 2, "manage": 1.5}}